towercrane/__init__.py
towercrane/cloud.py
towercrane/config.py
towercrane/db.py
towercrane/main.py
towercrane/progress.py
towercrane/tools.py
towercrane-1.1.dist-info/METADATA
towercrane-1.1.dist-info/WHEEL
towercrane-1.1.dist-info/entry_points.txt
towercrane-1.1.dist-info/top_level.txt
towercrane-1.1.dist-info/RECORD
