Metadata-Version: 2.1
Name: towercrane
Version: 1.1
Summary: TowerCrane helps you keep your large local datasets in the cloud
Home-page: https://github.com/ashtianicode
Author: Taha
Author-email: taha.m.ashtiani@gmail.com
License: MIT
Platform: UNKNOWN
Classifier: Environment :: Console
Classifier: Intended Audience :: Science/Research
Classifier: License :: OSI Approved :: GNU General Public License v3 (GPLv3)
Classifier: Programming Language :: Python :: 3.6
Classifier: Programming Language :: Python :: 3.7
Classifier: Operating System :: MacOS
Classifier: Operating System :: Unix
Classifier: Topic :: Office/Business :: Financial :: Investment
Requires-Dist: fire
Requires-Dist: boto3
Requires-Dist: db-sqlite3
Requires-Dist: zipfile36
Requires-Dist: tabulate
